ipyopt/__init__.py
ipyopt/ipyopt.cpython-310-x86_64-linux-gnu.so
ipyopt/ipyopt.pyi
ipyopt/optimize.py
ipyopt/py.typed
ipyopt/sym_compile.py
ipyopt.libs/libblas-0aa2fd44.so.3.12.0
ipyopt.libs/libcoinmumps-f7c4d0c4.so.3.0.9
ipyopt.libs/libgfortran-040039e1.so.5.0.0
ipyopt.libs/libipopt-abdf3ab6.so.1.10.12
ipyopt.libs/liblapack-bdb0018b.so.3.12.0
ipyopt.libs/libquadmath-96973f99.so.0.0.0
ipyopt-0.12.10.dist-info/METADATA
ipyopt-0.12.10.dist-info/WHEEL
ipyopt-0.12.10.dist-info/top_level.txt
ipyopt-0.12.10.dist-info/RECORD
ipyopt-0.12.10.dist-info/licenses/LICENSE
