Metadata-Version: 2.1
Name: ipyopt
Version: 0.12.10
Summary: Python interface to Ipopt
Author: Gerhard Bräunlich, Nikitas Rontsis
Author-email: Gerhard Bräunlich <g.braeunlich@disroot.org>, Nikitas Rontsis <nrontsis@gmail.com>
License: BSD 3-Clause License
Project-URL: Homepage, https://gitlab.com/ipyopt-devs/ipyopt
Project-URL: Documentation, https://ipyopt-devs.gitlab.io/ipyopt
Project-URL: Repository, https://gitlab.com/ipyopt-devs/ipyopt
Project-URL: Issues, https://gitlab.com/ipyopt-devs/ipyopt/-/issues
Classifier: Programming Language :: Python :: 3
Classifier: License :: OSI Approved :: BSD License
Requires-Python: >=3.6
License-File: LICENSE
Requires-Dist: numpy
